.coveragerc
.testr.conf
AUTHORS
ChangeLog
HACKING.rst
LICENSE
MANIFEST.in
README.rst
pylintrc
requirements-py3.txt
requirements.txt
run_tests.sh
setup.cfg
setup.py
test-requirements.txt
tox.ini
doc/.gitignore
doc/Makefile
doc/README.rst
doc/source/conf.py
doc/source/contributing.rst
doc/source/index.rst
doc/source/openstack_resources.rst
doc/source/releases.rst
doc/source/schema.rst
doc/source/terminology.rst
doc/source/man/satori.rst
doc/source/sourcecode/.gitignore
satori/__init__.py
satori/bash.py
satori/discovery.py
satori/dns.py
satori/errors.py
satori/serviceinstall.py
satori/shell.py
satori/smb.py
satori/ssh.py
satori/tunnel.py
satori/utils.py
satori.egg-info/PKG-INFO
satori.egg-info/SOURCES.txt
satori.egg-info/dependency_links.txt
satori.egg-info/entry_points.txt
satori.egg-info/not-zip-safe
satori.egg-info/requires.txt
satori.egg-info/test-requires.txt
satori.egg-info/top_level.txt
satori/common/__init__.py
satori/common/logging.py
satori/common/templating.py
satori/contrib/psexec.py
satori/formats/custom.jinja
satori/formats/text.jinja
satori/sysinfo/__init__.py
satori/sysinfo/blueprint.py
satori/sysinfo/facter.py
satori/sysinfo/ohai.py
satori/sysinfo/ohai_solo.py
satori/sysinfo/posh_ohai.py
tools/install_venv.py
tools/install_venv_common.py
tools/with_venv.sh